machitare/__init__.py
machitare-0.1.0.dist-info/LICENSE
machitare-0.1.0.dist-info/METADATA
machitare-0.1.0.dist-info/WHEEL
machitare-0.1.0.dist-info/RECORD
