Metadata-Version: 2.1
Name: machitare
Version: 0.1.0
Summary: Machitare is an innovative agent creation framework designed to revolutionize the way agents are built and deployed.
License: MIT
Author: SwiftyOS
Author-email: craigswift13@gmail.com
Requires-Python: >=3.12,<4.0
Classifier: License :: OSI Approved :: MIT License
Classifier: Programming Language :: Python :: 3
Classifier: Programming Language :: Python :: 3.12
